jembewf/__init__.py
jembewf/flow.py
jembewf/helpers.py
jembewf/process_mixin.py
jembewf/state.py
jembewf/step_mixin.py
jembewf/transition.py
jembewf-0.0.3.dist-info/LICENSE
jembewf-0.0.3.dist-info/METADATA
jembewf-0.0.3.dist-info/WHEEL
jembewf-0.0.3.dist-info/top_level.txt
jembewf-0.0.3.dist-info/RECORD
