Metadata-Version: 2.1
Name: jembewf
Version: 0.0.3
Summary: Jembe Workflow Management
Home-page: https://jembe.io
Author: Predrag Peranovic
Author-email: predrag.peranovic@jembe.io
License: LGPL-3.0-or-later
Project-URL: Repository, https://github.com/Jembe/jembewf
Keywords: ["workflows"]
Classifier: Development Status :: 3 - Alpha
Classifier: Environment :: Web Environment
Classifier: Framework :: Flask
Classifier: Intended Audience :: Developers
Classifier: License :: OSI Approved :: GNU Lesser General Public License v3 or later (LGPLv3+)
Classifier: Programming Language :: Python :: 3.10
Requires-Python: >=3.10
License-File: LICENSE
Requires-Dist: Flask
Requires-Dist: Flask-SQLAlchemy
Requires-Dist: sqlalchemy-json
Provides-Extra: dev
Requires-Dist: psycopg2 ; extra == 'dev'
Requires-Dist: psycopg ; extra == 'dev'
Requires-Dist: twine ; extra == 'dev'
Requires-Dist: build ; extra == 'dev'
Requires-Dist: black ; extra == 'dev'
Requires-Dist: pylint ; extra == 'dev'
Requires-Dist: pylint-flask ; extra == 'dev'
Requires-Dist: pylint-flask-sqlalchemy ; extra == 'dev'
Requires-Dist: mypy ; extra == 'dev'
Requires-Dist: pytest ; extra == 'dev'
Requires-Dist: pytest-flask-sqlalchemy ; extra == 'dev'
Requires-Dist: pytest-postgresql ; extra == 'dev'
Requires-Dist: coverage[toml] ; extra == 'dev'
Requires-Dist: watchdog[watchmedo] ; extra == 'dev'
